[{"division":"HUM","DDBJ":84030,"DDBJ_proportion":11.38,"EMBL":128413,"EMBL_proportion":17.4,"GenBank":525666,"GenBank_proportion":71.22,"Total":738109,"Total_proportion":"100.00"},
{"division":"PRI","DDBJ":20171,"DDBJ_proportion":13.64,"EMBL":7384,"EMBL_proportion":4.99,"GenBank":120309,"GenBank_proportion":81.36,"Total":147864,"Total_proportion":"100.00"},
{"division":"ROD","DDBJ":42354,"DDBJ_proportion":7.79,"EMBL":56822,"EMBL_proportion":10.45,"GenBank":444453,"GenBank_proportion":81.76,"Total":543629,"Total_proportion":"100.00"},
{"division":"MAM","DDBJ":24004,"DDBJ_proportion":4.66,"EMBL":50149,"EMBL_proportion":9.74,"GenBank":440598,"GenBank_proportion":85.59,"Total":514751,"Total_proportion":"100.00"},
{"division":"VRT","DDBJ":96199,"DDBJ_proportion":3.37,"EMBL":439371,"EMBL_proportion":15.4,"GenBank":2317561,"GenBank_proportion":81.23,"Total":2853131,"Total_proportion":"100.00"},
{"division":"INV","DDBJ":218491,"DDBJ_proportion":3,"EMBL":3141679,"EMBL_proportion":43.09,"GenBank":3930259,"GenBank_proportion":53.91,"Total":7290429,"Total_proportion":"100.00"},
{"division":"PLN","DDBJ":302778,"DDBJ_proportion":6.26,"EMBL":440142,"EMBL_proportion":9.1,"GenBank":4093185,"GenBank_proportion":84.64,"Total":4836105,"Total_proportion":"100.00"},
{"division":"BCT","DDBJ":131589,"DDBJ_proportion":7.82,"EMBL":149679,"EMBL_proportion":8.89,"GenBank":1402165,"GenBank_proportion":83.29,"Total":1683433,"Total_proportion":"100.00"},
{"division":"VRL","DDBJ":117092,"DDBJ_proportion":4.76,"EMBL":108346,"EMBL_proportion":4.4,"GenBank":2234240,"GenBank_proportion":90.83,"Total":2459678,"Total_proportion":"100.00"},
{"division":"PHG","DDBJ":410,"DDBJ_proportion":3.05,"EMBL":1113,"EMBL_proportion":8.27,"GenBank":11941,"GenBank_proportion":88.69,"Total":13464,"Total_proportion":"100.00"},
{"division":"ENV","DDBJ":321735,"DDBJ_proportion":3.6,"EMBL":673774,"EMBL_proportion":7.55,"GenBank":7934198,"GenBank_proportion":88.85,"Total":8929707,"Total_proportion":"100.00"},
{"division":"SYN","DDBJ":33441,"DDBJ_proportion":12.15,"EMBL":33624,"EMBL_proportion":12.22,"GenBank":208159,"GenBank_proportion":75.63,"Total":275224,"Total_proportion":"100.00"},
{"division":"EST","DDBJ":15989429,"DDBJ_proportion":20.7,"EMBL":6248937,"EMBL_proportion":8.09,"GenBank":54993959,"GenBank_proportion":71.21,"Total":77232325,"Total_proportion":"100.00"},
{"division":"TSA","DDBJ":9017002,"DDBJ_proportion":3.92,"EMBL":11665400,"EMBL_proportion":5.07,"GenBank":209544647,"GenBank_proportion":91.02,"Total":230227049,"Total_proportion":"100.00"},
{"division":"GSS","DDBJ":5320539,"DDBJ_proportion":13.21,"EMBL":4962490,"EMBL_proportion":12.33,"GenBank":29980026,"GenBank_proportion":74.46,"Total":40263055,"Total_proportion":"100.00"},
{"division":"HTC","DDBJ":310287,"DDBJ_proportion":54.2,"EMBL":150510,"EMBL_proportion":26.29,"GenBank":111675,"GenBank_proportion":19.51,"Total":572472,"Total_proportion":"100.00"},
{"division":"HTG","DDBJ":3656,"DDBJ_proportion":2.08,"EMBL":23873,"EMBL_proportion":13.57,"GenBank":148458,"GenBank_proportion":84.36,"Total":175987,"Total_proportion":"100.00"},
{"division":"STS","DDBJ":40133,"DDBJ_proportion":2.98,"EMBL":81787,"EMBL_proportion":6.07,"GenBank":1224947,"GenBank_proportion":90.95,"Total":1346867,"Total_proportion":"100.00"},
{"division":"PAT","DDBJ":14718404,"DDBJ_proportion":36.41,"EMBL":13581220,"EMBL_proportion":33.59,"GenBank":12128398,"GenBank_proportion":30,"Total":40428022,"Total_proportion":"100.00"},
{"division":"WGS","DDBJ":24361199,"DDBJ_proportion":2.49,"EMBL":643211974,"EMBL_proportion":65.72,"GenBank":311195739,"GenBank_proportion":31.79,"Total":978768912,"Total_proportion":"100.00"}]